{
  "users": [
    {
      "id": 1,
      "firstName": "Admin",
      "lastName": "",
      "username": "admin",
      "email": "admin@gmail.com",
      "password": "admin",
      "phone": "933-658-1213",
      "addres": "xxxxx",
      "status": true 
    }
  
  ],
  "products": [
    {
      "id": 1,
      "name": "Procesador Intel Core i9-10900K",
      "brand": "Intel",
      "type": "Procesador",
      "price": 599.99,
      "img": "https://images-na.ssl-images-amazon.com/images/I/61qUfPKfqJL.jpg",
      "available": true
    },
    {
      "id": 2,
      "name": "Tarjeta Gr치fica NVIDIA GeForce RTX 3080",
      "brand": "NVIDIA",
      "type": "Tarjeta Gr치fica",
      "price": 899.99,
      "img": "https://m.media-amazon.com/images/I/41e1zP76o7L.jpg",
      "available": true
    },
    {
      "id": 3,
      "name": "Memoria RAM Corsair Vengeance RGB Pro 16GB",
      "brand": "Corsair",
      "type": "Memoria RAM",
      "price": 129.99,
      "img": "https://m.media-amazon.com/images/I/51jnTiyHJUL.jpg",
      "available": false
    },
    {
      "id": 4,
      "name": "SSD Samsung 970 EVO Plus 1TB",
      "brand": "Samsung",
      "type": "SSD",
      "price": 199.99,
      "img": "https://m.media-amazon.com/images/I/41QZdNEpzAL.jpg",
      "available": true
    },
    {
      "id": 5,
      "name": "Procesador AMD Ryzen 9 5900X",
      "brand": "AMD",
      "type": "Procesador",
      "price": 549.99,
      "img": "https://m.media-amazon.com/images/I/51fNCtt4E3L.jpg",
      "available": true
    },
    {
      "id": 6,
      "name": "Tarjeta Gr치fica AMD Radeon RX 6800 XT",
      "brand": "AMD",
      "type": "Tarjeta Gr치fica",
      "price": 649.99,
      "img": "https://i.blogs.es/a22729/captura-de-pantalla-2020-11-18-a-las-20.55.29/original.png",
      "available": true
    },
    {
      "createdAt": 1718232144588,
      "modifiedAt": 1718232144588,
      "id": 7
    }
  ]
}